{"box_data": [{"position": {"minX": 145.556640625, "minY": 131.884765625, "maxX": 222.705078125, "maxY": 200.634765625}, "class_id": 0, "box_caption": "person 0.364", "scores": {"class_score": 0.3636728525161743}, "domain": "pixel"}, {"position": {"minX": 212.548828125, "minY": 152.9541015625, "maxX": 282.2265625, "maxY": 265.2587890625}, "class_id": 0, "box_caption": "person 0.256", "scores": {"class_score": 0.2564549446105957}, "domain": "pixel"}, {"position": {"minX": 60.9375, "minY": 214.1357421875, "maxX": 190.4296875, "maxY": 472.9248046875}, "class_id": 0, "box_caption": "person 0.195", "scores": {"class_score": 0.19466495513916016}, "domain": "pixel"}, {"position": {"minX": 140.4541015625, "minY": 167.48046875, "maxX": 221.2646484375, "maxY": 259.912109375}, "class_id": 0, "box_caption": "person 0.147", "scores": {"class_score": 0.1474442481994629}, "domain": "pixel"}, {"position": {"minX": 215.91796875, "minY": 151.708984375, "maxX": 279.541015625, "maxY": 215.771484375}, "class_id": 0, "box_caption": "person 0.134", "scores": {"class_score": 0.1341935396194458}, "domain": "pixel"}, {"position": {"minX": 159.130859375, "minY": 197.75390625, "maxX": 269.775390625, "maxY": 481.54296875}, "class_id": 0, "box_caption": "person 0.117", "scores": {"class_score": 0.11666786670684814}, "domain": "pixel"}, {"position": {"minX": 208.642578125, "minY": 187.158203125, "maxX": 275.390625, "maxY": 278.02734375}, "class_id": 0, "box_caption": "person 0.103", "scores": {"class_score": 0.10293391346931458}, "domain": "pixel"}, {"position": {"minX": 167.98095703125, "minY": 187.5244140625, "maxX": 272.76611328125, "maxY": 355.2978515625}, "class_id": 0, "box_caption": "person 0.096", "scores": {"class_score": 0.09589970111846924}, "domain": "pixel"}, {"position": {"minX": 208.72802734375, "minY": 181.33544921875, "maxX": 277.28271484375, "maxY": 339.83154296875}, "class_id": 0, "box_caption": "person 0.086", "scores": {"class_score": 0.08612960577011108}, "domain": "pixel"}, {"position": {"minX": 148.53515625, "minY": 179.38232421875, "maxX": 245.263671875, "maxY": 288.46435546875}, "class_id": 0, "box_caption": "person 0.060", "scores": {"class_score": 0.05980938673019409}, "domain": "pixel"}, {"position": {"minX": 68.93310546875, "minY": 196.630859375, "maxX": 269.90966796875, "maxY": 487.841796875}, "class_id": 0, "box_caption": "person 0.050", "scores": {"class_score": 0.05040931701660156}, "domain": "pixel"}, {"position": {"minX": 157.6416015625, "minY": 148.3642578125, "maxX": 226.1474609375, "maxY": 237.2802734375}, "class_id": 0, "box_caption": "person 0.042", "scores": {"class_score": 0.04192042350769043}, "domain": "pixel"}, {"position": {"minX": 122.5341796875, "minY": 135.70556640625, "maxX": 213.1591796875, "maxY": 231.01806640625}, "class_id": 0, "box_caption": "person 0.025", "scores": {"class_score": 0.025008022785186768}, "domain": "pixel"}, {"position": {"minX": 137.21923828125, "minY": 172.607421875, "maxX": 202.60009765625, "maxY": 242.529296875}, "class_id": 0, "box_caption": "person 0.025", "scores": {"class_score": 0.024525940418243408}, "domain": "pixel"}, {"position": {"minX": 66.12548828125, "minY": 209.9609375, "maxX": 180.96923828125, "maxY": 366.11328125}, "class_id": 0, "box_caption": "person 0.023", "scores": {"class_score": 0.02251969277858734}, "domain": "pixel"}, {"position": {"minX": 227.57568359375, "minY": 158.89892578125, "maxX": 284.70458984375, "maxY": 293.37158203125}, "class_id": 0, "box_caption": "person 0.022", "scores": {"class_score": 0.02187448740005493}, "domain": "pixel"}, {"position": {"minX": 179.541015625, "minY": 166.1376953125, "maxX": 278.564453125, "maxY": 302.0751953125}, "class_id": 0, "box_caption": "person 0.021", "scores": {"class_score": 0.021178722381591797}, "domain": "pixel"}, {"position": {"minX": 131.3720703125, "minY": 176.904296875, "maxX": 246.2158203125, "maxY": 341.259765625}, "class_id": 0, "box_caption": "person 0.021", "scores": {"class_score": 0.020949840545654297}, "domain": "pixel"}, {"position": {"minX": 101.416015625, "minY": 170.00732421875, "maxX": 220.751953125, "maxY": 297.15576171875}, "class_id": 0, "box_caption": "person 0.016", "scores": {"class_score": 0.01631547510623932}, "domain": "pixel"}, {"position": {"minX": 75.830078125, "minY": 197.3388671875, "maxX": 214.599609375, "maxY": 336.8896484375}, "class_id": 0, "box_caption": "person 0.016", "scores": {"class_score": 0.016239136457443237}, "domain": "pixel"}, {"position": {"minX": 160.55908203125, "minY": 132.2509765625, "maxX": 221.83837890625, "maxY": 184.1552734375}, "class_id": 0, "box_caption": "person 0.016", "scores": {"class_score": 0.016058534383773804}, "domain": "pixel"}, {"position": {"minX": 180.62744140625, "minY": 173.583984375, "maxX": 223.44970703125, "maxY": 238.916015625}, "class_id": 0, "box_caption": "person 0.015", "scores": {"class_score": 0.015102796256542206}, "domain": "pixel"}, {"position": {"minX": 102.734375, "minY": 184.85107421875, "maxX": 258.88671875, "maxY": 386.02294921875}, "class_id": 0, "box_caption": "person 0.015", "scores": {"class_score": 0.014841612428426743}, "domain": "pixel"}, {"position": {"minX": 188.6962890625, "minY": 147.6806640625, "maxX": 281.9091796875, "maxY": 243.3349609375}, "class_id": 0, "box_caption": "person 0.013", "scores": {"class_score": 0.013342678546905518}, "domain": "pixel"}, {"position": {"minX": 213.2080078125, "minY": 199.79248046875, "maxX": 273.3642578125, "maxY": 414.83154296875}, "class_id": 0, "box_caption": "person 0.013", "scores": {"class_score": 0.013237595558166504}, "domain": "pixel"}, {"position": {"minX": 237.2650146484375, "minY": 158.7158203125, "maxX": 283.2855224609375, "maxY": 222.5341796875}, "class_id": 0, "box_caption": "person 0.013", "scores": {"class_score": 0.012734875082969666}, "domain": "pixel"}, {"position": {"minX": 190.7470703125, "minY": 144.9462890625, "maxX": 264.6728515625, "maxY": 199.4384765625}, "class_id": 0, "box_caption": "person 0.012", "scores": {"class_score": 0.01175418496131897}, "domain": "pixel"}, {"position": {"minX": 156.072998046875, "minY": 183.97216796875, "maxX": 223.406982421875, "maxY": 251.84326171875}, "class_id": 0, "box_caption": "person 0.012", "scores": {"class_score": 0.011580213904380798}, "domain": "pixel"}, {"position": {"minX": 174.395751953125, "minY": 222.96142578125, "maxX": 261.700439453125, "maxY": 389.85595703125}, "class_id": 0, "box_caption": "person 0.007", "scores": {"class_score": 0.007130250334739685}, "domain": "pixel"}, {"position": {"minX": 168.3837890625, "minY": 139.385986328125, "maxX": 227.0263671875, "maxY": 197.833251953125}, "class_id": 0, "box_caption": "person 0.007", "scores": {"class_score": 0.007103925570845604}, "domain": "pixel"}, {"position": {"minX": 120.4833984375, "minY": 154.833984375, "maxX": 208.3740234375, "maxY": 268.603515625}, "class_id": 0, "box_caption": "person 0.006", "scores": {"class_score": 0.006395835429430008}, "domain": "pixel"}, {"position": {"minX": 168.27392578125, "minY": 184.375, "maxX": 234.24072265625, "maxY": 274.21875}, "class_id": 0, "box_caption": "person 0.006", "scores": {"class_score": 0.00574164092540741}, "domain": "pixel"}, {"position": {"minX": 193.1396484375, "minY": 190.106201171875, "maxX": 259.5458984375, "maxY": 269.549560546875}, "class_id": 0, "box_caption": "person 0.006", "scores": {"class_score": 0.005676724016666412}, "domain": "pixel"}, {"position": {"minX": 8.3251953125, "minY": 0.4150390625, "maxX": 95.4345703125, "maxY": 204.1259765625}, "class_id": 0, "box_caption": "person 0.005", "scores": {"class_score": 0.0053258612751960754}, "domain": "pixel"}, {"position": {"minX": 225.74462890625, "minY": 210.21728515625, "maxX": 280.87158203125, "maxY": 374.08447265625}, "class_id": 0, "box_caption": "person 0.004", "scores": {"class_score": 0.004253329709172249}, "domain": "pixel"}, {"position": {"minX": 131.99462890625, "minY": 133.21533203125, "maxX": 197.27783203125, "maxY": 205.04150390625}, "class_id": 0, "box_caption": "person 0.004", "scores": {"class_score": 0.00422157347202301}, "domain": "pixel"}, {"position": {"minX": 148.81591796875, "minY": 185.0341796875, "maxX": 222.79052734375, "maxY": 321.0693359375}, "class_id": 0, "box_caption": "person 0.004", "scores": {"class_score": 0.004170594736933708}, "domain": "pixel"}, {"position": {"minX": 178.91845703125, "minY": 174.176025390625, "maxX": 267.15087890625, "maxY": 263.043212890625}, "class_id": 0, "box_caption": "person 0.004", "scores": {"class_score": 0.003787994384765625}, "domain": "pixel"}, {"position": {"minX": 68.5302734375, "minY": 210.400390625, "maxX": 153.3447265625, "maxY": 335.205078125}, "class_id": 0, "box_caption": "person 0.004", "scores": {"class_score": 0.0035443156957626343}, "domain": "pixel"}, {"position": {"minX": 130.615234375, "minY": 160.55908203125, "maxX": 194.677734375, "maxY": 230.48095703125}, "class_id": 0, "box_caption": "person 0.003", "scores": {"class_score": 0.003243035636842251}, "domain": "pixel"}, {"position": {"minX": 220.684814453125, "minY": 151.5625, "maxX": 265.679931640625, "maxY": 205.615234375}, "class_id": 0, "box_caption": "person 0.003", "scores": {"class_score": 0.003191683441400528}, "domain": "pixel"}, {"position": {"minX": 187.04833984375, "minY": 167.00439453125, "maxX": 243.98193359375, "maxY": 246.54541015625}, "class_id": 0, "box_caption": "person 0.003", "scores": {"class_score": 0.0031661801040172577}, "domain": "pixel"}, {"position": {"minX": 113.63525390625, "minY": 213.22021484375, "maxX": 191.22314453125, "maxY": 328.55224609375}, "class_id": 0, "box_caption": "person 0.002", "scores": {"class_score": 0.0019997917115688324}, "domain": "pixel"}, {"position": {"minX": 205.01708984375, "minY": 140.6982421875, "maxX": 292.32177734375, "maxY": 219.4580078125}, "class_id": 0, "box_caption": "person 0.002", "scores": {"class_score": 0.00171974441036582}, "domain": "pixel"}, {"position": {"minX": 72.3388671875, "minY": 152.4658203125, "maxX": 206.0302734375, "maxY": 281.2744140625}, "class_id": 0, "box_caption": "person 0.002", "scores": {"class_score": 0.0016542095690965652}, "domain": "pixel"}, {"position": {"minX": 213.34228515625, "minY": 156.884765625, "maxX": 302.99072265625, "maxY": 301.611328125}, "class_id": 0, "box_caption": "person 0.002", "scores": {"class_score": 0.0016208505257964134}, "domain": "pixel"}, {"position": {"minX": 139.825439453125, "minY": 129.571533203125, "maxX": 208.575439453125, "maxY": 184.405517578125}, "class_id": 0, "box_caption": "person 0.002", "scores": {"class_score": 0.0016091922298073769}, "domain": "pixel"}, {"position": {"minX": 232.11669921875, "minY": 240.936279296875, "maxX": 271.17919921875, "maxY": 389.471435546875}, "class_id": 0, "box_caption": "person 0.002", "scores": {"class_score": 0.0015219487249851227}, "domain": "pixel"}, {"position": {"minX": 169.3359375, "minY": 133.7890625, "maxX": 281.93359375, "maxY": 213.232421875}, "class_id": 0, "box_caption": "person 0.001", "scores": {"class_score": 0.0014992402866482735}, "domain": "pixel"}, {"position": {"minX": 136.29150390625, "minY": 176.4984130859375, "maxX": 185.72998046875, "maxY": 229.3792724609375}, "class_id": 0, "box_caption": "person 0.001", "scores": {"class_score": 0.0014419052749872208}, "domain": "pixel"}, {"position": {"minX": 213.92822265625, "minY": 149.9755859375, "maxX": 301.86767578125, "maxY": 237.1337890625}, "class_id": 0, "box_caption": "person 0.001", "scores": {"class_score": 0.001386262010782957}, "domain": "pixel"}, {"position": {"minX": 69.4580078125, "minY": 175.341796875, "maxX": 188.7939453125, "maxY": 311.962890625}, "class_id": 0, "box_caption": "person 0.001", "scores": {"class_score": 0.0013093496672809124}, "domain": "pixel"}, {"position": {"minX": 231.243896484375, "minY": 147.9736328125, "maxX": 287.884521484375, "maxY": 210.2783203125}, "class_id": 0, "box_caption": "person 0.001", "scores": {"class_score": 0.0011456944048404694}, "domain": "pixel"}, {"position": {"minX": 240.533447265625, "minY": 194.805908203125, "maxX": 288.189697265625, "maxY": 340.509033203125}, "class_id": 0, "box_caption": "person 0.001", "scores": {"class_score": 0.0011383574455976486}, "domain": "pixel"}, {"position": {"minX": 110.85205078125, "minY": 173.712158203125, "maxX": 183.60595703125, "maxY": 261.651611328125}, "class_id": 0, "box_caption": "person 0.001", "scores": {"class_score": 0.001101088710129261}, "domain": "pixel"}, {"position": {"minX": 223.5107421875, "minY": 154.89501953125, "maxX": 271.630859375, "maxY": 237.02392578125}, "class_id": 0, "box_caption": "person 0.001", "scores": {"class_score": 0.0010353494435548782}, "domain": "pixel"}], "class_labels": {"0": "person"}}